webots/__init__.py
webots/_utils.py
webots/controller.py
webots/vehicle.py
webots-0.0.1.dist-info/METADATA
webots-0.0.1.dist-info/WHEEL
webots-0.0.1.dist-info/top_level.txt
webots-0.0.1.dist-info/RECORD
