Metadata-Version: 2.1
Name: webots
Version: 0.0.1
Summary: Python package for Webots robot simulator
Home-page: UNKNOWN
Author: UNKNOWN
Author-email: UNKNOWN
License: Apache
Platform: noarch
